taurus_datamover/__init__.py
taurus_datamover/_datamover.py
taurus_datamover/_mock.py
taurus_datamover/mock_cluster_files/dtwrapper
taurus_datamover/mock_cluster_files/ws_allocate
taurus_datamover/mock_cluster_files/ws_list
taurus_datamover/mock_cluster_files/ws_release
taurus_datamover-0.4.0.dist-info/LICENSE
taurus_datamover-0.4.0.dist-info/METADATA
taurus_datamover-0.4.0.dist-info/WHEEL
taurus_datamover-0.4.0.dist-info/top_level.txt
taurus_datamover-0.4.0.dist-info/RECORD
