Metadata-Version: 2.1
Name: taurus-datamover
Version: 0.4.0
Summary: Python wrapper for the datamover tools that enable moving data between the ZIH fileserver and the taurus cluster at TU Dresden
Home-page: https://gitlab.mn.tu-dresden.de/bia-pol/taurus-datamover/
Author: Till Korten
Author-email: till.korten@tu-dresden.de
Classifier: Programming Language :: Python :: 3
Classifier: License :: OSI Approved :: BSD License
Classifier: Operating System :: OS Independent
Classifier: Intended Audience :: Science/Research
Classifier: Development Status :: 3 - Alpha
Requires-Python: >=3.6
License-File: LICENSE
